content_moderation_system/__init__.py
content_moderation_system/cms.py
content_moderation_system-0.121.dist-info/METADATA
content_moderation_system-0.121.dist-info/WHEEL
content_moderation_system-0.121.dist-info/top_level.txt
content_moderation_system-0.121.dist-info/RECORD
