Metadata-Version: 2.1
Name: content-moderation-system
Version: 0.121
Summary: A Python library for interacting with CMS APIs
Home-page: https://github.com/tanmaydoesai/content_moderation_system
Author: Tanmay Jain
Author-email: tanmay5tj@gmail.com
Classifier: Programming Language :: Python :: 3
Classifier: License :: OSI Approved :: MIT License
Classifier: Operating System :: OS Independent
Requires-Dist: requests
